hlepor/__init__.py
hlepor/hlepor.py
hlepor/setup.py
hLepor-0.0.4.dist-info/LICENSE
hLepor-0.0.4.dist-info/METADATA
hLepor-0.0.4.dist-info/WHEEL
hLepor-0.0.4.dist-info/top_level.txt
hLepor-0.0.4.dist-info/RECORD
