Metadata-Version: 2.1
Name: hLepor
Version: 0.0.4
Summary: This is Python port of original algorithm by Aaron Li-Feng Han
Home-page: https://github.com/logrusglobal/hLepor-python-port
Author: Irina Sorokina, Gleb Erofeev, Serge Gladkoff
Author-email: rd@logrusglobal.com
License: Apache Software License
Project-URL: Bug Tracker, https://github.com/pypa/sampleproject/issues
Platform: UNKNOWN
Classifier: Programming Language :: Python :: 3
Classifier: License :: OSI Approved :: Apache Software License
Classifier: Operating System :: OS Independent
Requires-Python: >=3.6
